django_project_initializer/__init__.py
django_project_initializer-1.0.4.dist-info/METADATA
django_project_initializer-1.0.4.dist-info/WHEEL
django_project_initializer-1.0.4.dist-info/entry_points.txt
django_project_initializer-1.0.4.dist-info/licenses/LICENSE
django_project_initializer-1.0.4.dist-info/RECORD
