Metadata-Version: 2.4
Name: django_project_initializer
Version: 1.0.4
Summary: The Django Project Initializer is a helper Python script that initializes a Modified Django project with mysql and python-stubs out-of-the-box.
Project-URL: Homepage, https://github.com/AdrianJames27/django_project_initializer
Project-URL: Issues, https://github.com/AdrianJames27/django_project_initializer/issues
Author-email: AdrianJames27 <bonbon22135@gmail.com>
License-File: LICENSE
Classifier: License :: OSI Approved :: GNU General Public License v3 (GPLv3)
Classifier: Operating System :: OS Independent
Classifier: Programming Language :: Python :: 3
Requires-Python: >=3.12
